LICENSE
README.md
build.zig
build.zig.zon
chat.zig
dungeon.zig
index.html
main.py
object.zig
pyproject.toml
setup.py
terrain.zig
walk.zig
zigger.egg-info/PKG-INFO
zigger.egg-info/SOURCES.txt
zigger.egg-info/dependency_links.txt
zigger.egg-info/entry_points.txt
zigger.egg-info/not-zip-safe
zigger.egg-info/requires.txt
zigger.egg-info/top_level.txt