Metadata-Version: 2.4
Name: zigger
Version: 0.0.1a1
Summary: Terrain Zigger
Home-page: https://github.com/JosefAlbers/TerrainZigger
Author: J Joe
Author-email: albersj66@gmail.com
License-File: LICENSE
Requires-Dist: ziglang==0.13.0.post1
Requires-Dist: numpy
Requires-Dist: requests
Dynamic: author
Dynamic: author-email
Dynamic: description
Dynamic: description-content-type
Dynamic: home-page
Dynamic: license-file
Dynamic: requires-dist
Dynamic: summary
